.babelrc
.gitignore
CHANGELOG.md
Dockerfile
LICENSE
MANIFEST.in
Makefile
README.md
clusterapp.py
clustermgr.service
clustermgr4-cli
get_remote_stats.py
package-lock.json
package.json
requirements-dev.txt
requirements.txt
rhel7-centos7-install.md
setup.py
static_build.md
webpack.config.js
.github/workflows/releaseplease.yml
.github/workflows/uploadrelease.yml
clustermgr/__init__.py
clustermgr/application.py
clustermgr/config.py
clustermgr/extensions.py
clustermgr/forms.py
clustermgr/get_remote_stats.py
clustermgr/models.py
clustermgr/monitoring_defs.py
clustermgr/version.py
clustermgr/weblogger.py
clustermgr/core/__init__.py
clustermgr/core/change_gluu_host.py
clustermgr/core/clustermgr_installer.py
clustermgr/core/clustermgr_logging.py
clustermgr/core/jproperties.py
clustermgr/core/ldap_cache_cleanup.py
clustermgr/core/ldap_functions.py
clustermgr/core/license.py
clustermgr/core/msgcon.py
clustermgr/core/ox11.py
clustermgr/core/proplist.json
clustermgr/core/remote.py
clustermgr/core/six.py
clustermgr/core/utils.py
clustermgr/migrations/README
clustermgr/migrations/alembic.ini
clustermgr/migrations/env.py
clustermgr/migrations/script.py.mako
clustermgr/migrations/versions/0c35f58a2e73_.py
clustermgr/migrations/versions/0e7453df1644_update_keyrotation.py
clustermgr/migrations/versions/198c383101dd_update_appconfiguration.py
clustermgr/migrations/versions/22f6c85b4b24_.py
clustermgr/migrations/versions/2926b8ffa2f0_.py
clustermgr/migrations/versions/2a0c96ff52f6_add_admin_email_field.py
clustermgr/migrations/versions/325c760b3ec7_add_ssh_port.py
clustermgr/migrations/versions/3ca18f178674_add_nginx_os.py
clustermgr/migrations/versions/4fca7c65b3df_add_nginx_ip_column_to_appconfig.py
clustermgr/migrations/versions/5246a3f7a7e4_consolidated_all_server_models.py
clustermgr/migrations/versions/555f03405e07_add_cacheserver.py
clustermgr/migrations/versions/55c791eac900_.py
clustermgr/migrations/versions/59f615b01c3e_add_nginx_os_type_to_appconfiguration.py
clustermgr4.egg-info/PKG-INFO
clustermgr4.egg-info/SOURCES.txt
clustermgr4.egg-info/dependency_links.txt
clustermgr4.egg-info/not-zip-safe
clustermgr4.egg-info/requires.txt
clustermgr4.egg-info/top_level.txt
