Metadata-Version: 2.1
Name: clustermgr4
Version: 4.4.post4
Summary: Tool to facilitate LDAP replication, key management and log centralization for the Gluu Server
Home-page: https://github.com/GluuFederation/cluster-mgr/tree/4.0/clustermgr
Author: Gluu
Author-email: support@gluu.org
License: All Rights Reserved
Platform: UNKNOWN
Classifier: Development Status :: 4 - Beta
Classifier: Environment :: Web Environment
Classifier: Framework :: Flask
Classifier: Intended Audience :: System Administrators
Classifier: License :: Other/Proprietary License
Classifier: Operating System :: POSIX :: Linux
Classifier: Programming Language :: Python :: 3.7
Classifier: Programming Language :: Python :: 3 :: Only
Classifier: Topic :: System :: Logging
Classifier: Topic :: System :: Monitoring
Classifier: Topic :: System :: Systems Administration
License-File: LICENSE
